rpsarena/__init__.py
rpsarena/__main__.py
rpsarena-0.1.0.dist-info/METADATA
rpsarena-0.1.0.dist-info/WHEEL
rpsarena-0.1.0.dist-info/entry_points.txt
rpsarena-0.1.0.dist-info/top_level.txt
rpsarena-0.1.0.dist-info/RECORD
