Metadata-Version: 2.4
Name: rpsarena
Version: 0.1.0
Summary: A simulation of Rock Paper Scissors units chasing each other in a GUI window. Highly configurable.
Author: Al Sweigart
Classifier: Programming Language :: Python
Classifier: Programming Language :: Python :: 3
Classifier: Topic :: Games/Entertainment :: Simulation
Classifier: Topic :: Scientific/Engineering :: Artificial Life
Classifier: License :: OSI Approved :: MIT License
Requires-Python: >=3.2
